aredis_om/__init__.py
aredis_om/_compat.py
aredis_om/async_redis.py
aredis_om/checks.py
aredis_om/connections.py
aredis_om/model/__init__.py
aredis_om/model/cli/__init__.py
aredis_om/model/cli/migrate.py
aredis_om/model/encoders.py
aredis_om/model/migrations/__init__.py
aredis_om/model/migrations/migrator.py
aredis_om/model/model.py
aredis_om/model/query_resolver.py
aredis_om/model/render_tree.py
aredis_om/model/token_escaper.py
aredis_om/sync_redis.py
aredis_om/util.py
pyredis_om-0.4.0.dist-info/LICENSE
pyredis_om-0.4.0.dist-info/METADATA
pyredis_om-0.4.0.dist-info/WHEEL
pyredis_om-0.4.0.dist-info/entry_points.txt
pyredis_om-0.4.0.dist-info/RECORD
