Metadata-Version: 2.3
Name: pyredis-om
Version: 0.4.0
Summary: A true `redis-om` alternative, built out of frustration.
License: BSD-3-Clause
Author: Redis OSS
Author-email: oss@redis.com
Maintainer: Srikanth
Maintainer-email: srikanth@psync.dev
Requires-Python: >=3.10,<4.0
Classifier: Development Status :: 4 - Beta
Classifier: Environment :: Console
Classifier: Intended Audience :: Developers
Classifier: License :: OSI Approved :: BSD License
Classifier: Operating System :: OS Independent
Classifier: Programming Language :: Python
Classifier: Programming Language :: Python :: 3
Classifier: Programming Language :: Python :: 3.10
Classifier: Programming Language :: Python :: 3.11
Classifier: Programming Language :: Python :: 3.12
Classifier: Programming Language :: Python :: 3.13
Classifier: Programming Language :: Python :: 3.14
Classifier: Topic :: Database
Requires-Dist: click (>=8.1.7,<9.0.0)
Requires-Dist: hiredis (>=3.2.1,<4.0.0)
Requires-Dist: more-itertools (>=10.7.0,<11.0.0)
Requires-Dist: pydantic (>=1.10.22)
Requires-Dist: python-ulid (>=3.0.0,<4.0.0)
Requires-Dist: redis (>=6.2.0,<7.0.0)
Requires-Dist: types-redis (>=4.6.0,<5.0.0)
Project-URL: Code, https://github.com/xchikux/redis-om-python
Project-URL: Issue tracker, https://github.com/xchikux/redis-om-python/issues
Project-URL: Repository, https://github.com/xchikux/redis-om-python
